basics/siso/siso.vhdl
library IEEE;
use IEEE.std_logic_1164.all;

entity siso is
    Port (d,clk,clear : in std_logic; q : inout std_logic);
end siso;

architecture behav of siso is
    signal x : std_logic_vector(3 downto 0) := "0000";
begin
    process(x,clk,clear)
    begin
        if (clear = '1') then
            q <= '0';
            x <= "0000";
        elsif (rising_edge(clk)) then
            x(0) <= d;
            for i in 0 to 2 loop
                x(i+1) <= x(i);
            end loop;
            q <= x(3);
        else 
            q <= q;
        end if;
    end process;
end behav;

basics/siso/siso_tb.vhdl
library IEEE;
use IEEE.std_logic_1164.all;

entity siso_tb is
end siso_tb;

architecture behavior of siso_tb is
    -- Component Declaration for the Unit Under Test (UUT)
    component siso
        Port (d,clk,clear : in std_logic; q : inout std_logic);
    end component;
    
    -- Inputs
    signal d : std_logic := '0';
    signal clk : std_logic := '0';
    signal clear : std_logic := '0';
    
    -- BiDirs
    signal q : std_logic;
    
    -- Clock period definitions
    constant clk_period : time := 10 ns;
begin
    -- Instantiate the Unit Under Test (UUT)
    uut: siso PORT MAP (
        d => d,
        clk => clk,
        clear => clear,
        q => q
    );
    
    -- Clock process
    clk_process: process
    begin
        clk <= '0';
        wait for clk_period/2;
        clk <= '1';
        wait for clk_period/2;
    end process;
    
    -- Stimulus process
    stim_proc: process
    begin
        wait for 10 ns;
        wait for clk_period*1;
        -- Initialize
        d <= '1', '0' after 30 ns, '1' after 50 ns, '0' after 90 ns;
        clear <= '1', '0' after 10 ns;
        wait;
        end process;
end;

siso/siso.vcd
$date
  Mon Nov 25 00:01:46 2024
$end
$version
  GHDL v0
$end
$timescale
  1 fs
$end
$scope module standard $end
$upscope $end
$scope module std_logic_1164 $end
$upscope $end
$scope module siso_tb $end
$var reg 1 ! d $end
$var reg 1 " clk $end
$var reg 1 # clear $end
$var reg 1 $ q $end
$scope module uut $end
$var reg 1 % d $end
$var reg 1 & clk $end
$var reg 1 ' clear $end
$var reg 1 ( q $end
$var reg 4 ) x[3:0] $end
$upscope $end
$upscope $end
$enddefinitions $end
#0
0!
0"
0#
U$
0%
0&
0'
U(
b0000 )
#5000000
1"
0$
1&
0(
#10000000
0"
0&
#15000000
1"
1&
#20000000
1!
0"
1#
1%
0&
1'
#25000000
1"
1&
#30000000
0"
0#
0&
0'
#35000000
1"
1&
b0001 )
#40000000
0"
0&
#45000000
1"
1&
b0011 )
#50000000
0!
0"
0%
0&
#55000000
1"
1&
b0110 )
#60000000
0"
0&
#65000000
1"
1&
b1100 )
#70000000
1!
0"
1%
0&
#75000000
1"
1$
1&
1(
b1001 )
#80000000
0"
0&
#85000000
1"
1&
b0011 )
#90000000
0"
0&
#95000000
1"
0$
1&
0(
b0111 )
